cobra/__init__.py
cobra/asset/__init__.py
cobra/asset/asset.py
cobra/robot/__init__.py
cobra/robot/robot.py
cobra/solution/__init__.py
cobra/solution/solution.py
cobra/task/__init__.py
cobra/task/task.py
cobra/user/user.py
cobra/utils/__init__.py
cobra/utils/caches.py
cobra/utils/cobra.config.sample
cobra/utils/configurations.py
cobra/utils/logging.py
cobra/utils/requests.py
cobra/utils/schema.py
cobra/utils/urls.py
cobra/utils/utils.py
cobra_io-0.0.8.dist-info/LICENSE
cobra_io-0.0.8.dist-info/METADATA
cobra_io-0.0.8.dist-info/WHEEL
cobra_io-0.0.8.dist-info/top_level.txt
cobra_io-0.0.8.dist-info/RECORD
