Metadata-Version: 2.1
Name: cobra-io
Version: 0.0.8
Summary: Composable Benchmark for Robotics Applications - Input/Output
Author-email: Matthias Mayer <matthias.mayer@tum.de>
License: MIT
Project-URL: Source Code, https://gitlab.lrz.de/tum-cps/cobra-io
Project-URL: Documentation, https://cobra-io.readthedocs.io/en/latest/
Project-URL: Bug Tracker, https://gitlab.lrz.de/tum-cps/cobra-io/-/issues
Keywords: Modular Reconfigurable Robots,Robot Design,Model Generation,Simulation,Benchmark,Path Planning
Classifier: License :: OSI Approved :: MIT License
Classifier: Programming Language :: Python
Classifier: Programming Language :: Python :: 3
Classifier: Programming Language :: Python :: 3 :: Only
Requires-Python: >=3.7
License-File: LICENSE
Requires-Dist: jsonschema>=4.10
Requires-Dist: requests>=2.28.1
Requires-Dist: requests-ratelimiter>=0.6.0
Requires-Dist: requests-cache>=0.7.0
Requires-Dist: referencing>=0.35.0
Provides-Extra: dev
Requires-Dist: flake8>=5.0; extra == "dev"
Requires-Dist: coverage>=6.3; extra == "dev"
Requires-Dist: pre-commit; extra == "dev"
Requires-Dist: pip-tools; extra == "dev"
Requires-Dist: pytest>=6.0; extra == "dev"
Requires-Dist: setuptools>=61.0.0; extra == "dev"
Requires-Dist: timor-python>=1.0.0; extra == "dev"
Requires-Dist: nb-clean; extra == "dev"
Requires-Dist: nbconvert; extra == "dev"
Requires-Dist: nbformat; extra == "dev"
Provides-Extra: full
Requires-Dist: cobra-io[dev]; extra == "full"
Requires-Dist: notebook; extra == "full"
